{
  "id": "1media",
  "name": "Bedroom",
  "description": "Description",
  "image": "Bedroom",
  "difficulty": 1,
  "scene": "Bedroom",
  "playerTransform": {
    "position": { "x": 0, "y": -0.2377, "z": 0 },
    "rotation": { "x": 0, "y": 74.26, "z": 0 }
  },
  "assistantTransform": {
    "position": { "x": 1.784284, "y": -0.155, "z": 0.717057 },
    "rotation": { "x": 0, "y": -111.17, "z": 0 },
    "scale": { "x": 0.7, "y": 0.7, "z": 0.7 }
  },
  "eventGroups": [
    {
      "type": "TouchManager",
      "eventGroupObjs": {
        "selectablesToActivate": [
          {
            "prefab": "Flashlight"
          }
        ],
        "selectablesToDeactivate": ["Flashlight"],
        "othersToDeactivate": ["Spotlight"]
      },
      "events": [
        {
          "parameters": {
            "correctSelectables": ["Flashlight"],
            "objsToActivate": { "prefab": "Spotlight" }
          },
          "instructions": {
            "request": ["Light the torchlight.", "Set the torch alight."],
            "correct": ["Well done!"],
            "wrong": ["Sorry, try again."]
          }
        }
      ]
    },
    {
      "type": "DragMoveManager",
      "eventGroupObjs": {
        "interactablesToActivate": [
          {
            "prefab": "Brush"
          }
        ],
        "interactablesToDeactivate": ["Brush"],
        "targetsToActivate": [
          {
            "prefab": "CatCollider1"
          },
          {
            "prefab": "CatCollider2"
          },
          {
            "prefab": "CatCollider3"
          }
        ],
        "targetsToDeactivate": ["CatCollider1", "CatCollider2", "CatCollider3"],
        "othersToActivate": [
          {
            "prefab": "GreyCat1"
          }
        ],
        "othersToDeactivate": ["GreyCat1"]
      },
      "events": [
        {
          "parameters": {
            "correctInteractables": ["Brush"],
            "correctTargets": ["CatCollider1", "CatCollider2", "CatCollider3"],
            "numericParameter": 3
          },
          "instructions": {
            "request": [
              "Take the comb and brush the cat’s coat.",
              "Grab the brush and comb the cat’s fur."
            ],
            "correct": ["Well done!"],
            "wrong": ["Sorry, try again."]
          }
        }
      ]
    },
    {
      "type": "TouchManager",
      "eventGroupObjs": {
        "selectablesToActivate": [
          {
            "prefab": "Laptop_black_off"
          }
        ],
        "selectablesToDeactivate": ["Laptop_black_off"],
        "othersToDeactivate": ["hills"]
      },
      "events": [
        {
          "parameters": {
            "correctSelectables": ["Laptop_black_off"],
            "objsToActivate": { "prefab": "hills" }
          },
          "instructions": {
            "request": ["Switch the laptop on.", "Turn the laptop on."],
            "correct": ["Well done!"],
            "wrong": ["Sorry, try again."]
          }
        }
      ]
    },
    {
      "type": "DragMoveManager",
      "eventGroupObjs": {
        "interactablesToActivate": [
          {
            "prefab": "Pen_blue"
          }
        ],
        "interactablesToDeactivate": ["Pen_blue"],
        "targetsToActivate": [
          {
            "prefab": "Notepad"
          }
        ],
        "targetsToDeactivate": ["Notepad"],
        "othersToActivate": [
          {
            "prefab": "Pen_cap_blue"
          }
        ],
        "othersToDeactivate": ["Pen_cap_blue"]
      },
      "events": [
        {
          "parameters": {
            "correctInteractables": ["Pen_blue"],
            "correctTargets": ["Notepad"],
            "numericParameter": 1
          },
          "instructions": {
            "request": ["Make a note in the diary.", "Write in the diary."],
            "correct": ["Well done!"],
            "wrong": ["Sorry, try again."]
          }
        }
      ]
    },
    {
      "type": "DragMoveManager",
      "eventGroupObjs": {
        "interactablesToActivate": [
          {
            "prefab": "Highlighter_pen_blue"
          },
          {
            "prefab": "Highlighter_pen_green"
          },
          {
            "prefab": "Highlighter_pen_pink"
          },
          {
            "prefab": "Highlighter_pen_yellow"
          }
        ],
        "interactablesToDeactivate": [
          "Highlighter_pen_blue",
          "Highlighter_pen_green",
          "Highlighter_pen_pink",
          "Highlighter_pen_yellow"
        ],
        "targetsToActivate": [
          {
            "prefab": "BookCollider1"
          },
          {
            "prefab": "BookCollider2"
          },
          {
            "prefab": "BookCollider3"
          },
          {
            "prefab": "BookCollider4"
          }
        ],
        "targetsToDeactivate": [
          "BookCollider1",
          "BookCollider2",
          "BookCollider3",
          "BookCollider4"
        ],
        "othersToActivate": [
          {
            "prefab": "Book"
          }
        ],
        "othersToDeactivate": ["Book"]
      },
      "events": [
        {
          "parameters": {
            "correctInteractables": ["Highlighter_pen_green"],
            "correctTargets": [
              "BookCollider1",
              "BookCollider2",
              "BookCollider3",
              "BookCollider4"
            ],
            "numericParameter": 1
          },
          "instructions": {
            "request": [
              "Underline the book title with a green marker.",
              "Highlight the book title with a green marker."
            ],
            "correct": ["Well done!"],
            "wrong": ["Sorry, try again."]
          }
        }
      ]
    },
    {
      "type": "DragReleaseManager",
      "eventGroupObjs": {
        "interactablesToActivate": [
          {
            "prefab": "TShirt_Folded_Yellow"
          }
        ],
        "interactablesToDeactivate": ["TShirt_Folded_Yellow"],
        "targetsToActivate": [
          {
            "prefab": "TshirtTarget"
          }
        ]
      },
      "events": [
        {
          "parameters": {
            "correctInteractables": ["TShirt_Folded_Yellow"],
            "correctTargets": ["TshirtTarget"],
            "finalTransform": {
              "position": { "x": -1.105224, "y": 0.502416, "z": 1.83927 },
              "rotation": { "x": 3.142, "y": 1.062, "z": -6.804 }
            },
            "objsToDeactivate": ["TshirtTarget"]
          },
          "instructions": {
            "request": [
              "Put the t-shirt on the pillow",
              "Place the t-shirt on the cushion "
            ],
            "correct": ["Well done!"],
            "wrong": ["Sorry, try again."]
          }
        }
      ]
    },
    {
      "type": "DragReleaseManager",
      "eventGroupObjs": {
        "interactablesToActivate": [
          {
            "prefab": "Poster"
          }
        ],
        "interactablesToDeactivate": ["Poster"],
        "targetsToActivate": [
          {
            "prefab": "PosterTarget"
          }
        ],
        "othersToActivate": ["Arrow"]
      },
      "events": [
        {
          "parameters": {
            "correctInteractables": ["Poster"],
            "correctTargets": ["PosterTarget"],
            "finalTransform": {
              "position": { "x": 2.235, "y": 1.415, "z": -0.291 },
              "rotation": { "x": 0, "y": 90, "z": 0 }
            },
            "objsToDeactivate": ["PosterTarget", "Arrow"]
          },
          "instructions": {
            "request": [
              "Stick the poster on the wall.",
              "Attach the poster on the wall."
            ],
            "correct": ["Well done!"],
            "wrong": ["Sorry, try again."]
          }
        }
      ]
    }
  ]
}
